asgimiddleware-0.1.9.dist-info/METADATA
asgimiddleware-0.1.9.dist-info/WHEEL
asgimiddleware-0.1.9.dist-info/entry_points.txt
asgimiddleware-0.1.9.dist-info/licenses/LICENSE.txt
asgimiddlewares/__init__.py
asgimiddlewares/custom_exception.py
asgimiddlewares/custom_header.py
asgimiddlewares/extended_logging.py
asgimiddlewares/path_id.py
asgimiddlewares/prometheus.py
asgimiddlewares/request_time.py
asgimiddlewares/routing.py
asgimiddlewares/utils.py
asgimiddleware-0.1.9.dist-info/RECORD
