Metadata-Version: 2.1
Name: ASGIMiddleware
Version: 0.1.9
Summary: Connexion-based ASGI Middleware collection
Author: Red Hat Release Engineering
Author-Email: mszymutk <mszymutk@redhat.com>
License: MIT
Project-URL: Homepage, https://github.com/release-engineering/ASGI-Middlewares
Project-URL: Issues, https://github.com/release-engineering/ASGI-Middlewares/issues
Requires-Python: >=3.10
Requires-Dist: starlette>=0.37.2
Requires-Dist: connexion>=3.1.0
Requires-Dist: prometheus-client>=0.20.0
